djdt_permissions/__init__.py
djdt_permissions/apps.py
djdt_permissions/panels/__init__.py
djdt_permissions/panels/permissions_panel.py
djdt_permissions/templates/djdt_permissions/group_tr.html
djdt_permissions/templates/djdt_permissions/permissions_panel.html
djdt_permissions/tests/__init__.py
djdt_permissions/tests/test_permissions_panel.py
djdt_permissions-1.0.2.dist-info/LICENSE
djdt_permissions-1.0.2.dist-info/METADATA
djdt_permissions-1.0.2.dist-info/WHEEL
djdt_permissions-1.0.2.dist-info/RECORD
