Metadata-Version: 2.1
Name: djdt-permissions
Version: 1.0.2
Summary: A panel for Django Debug Toolbar (DjDT) to display the current user's permissions.
Home-page: https://github.com/baudhuina/djdt-permissions
License: BSD-3-Clause
Keywords: Django Debug Toolbar,DJdT,django-toolbar
Author: Alain Baudhuin
Author-email: alain.baudhuin@skynet.be
Requires-Python: >=3.8,<4.0
Classifier: Development Status :: 5 - Production/Stable
Classifier: Environment :: Web Environment
Classifier: Framework :: Django
Classifier: Framework :: Django :: 3.2
Classifier: Framework :: Django :: 4.0
Classifier: Framework :: Django :: 4.1
Classifier: Framework :: Django :: 4.2
Classifier: Intended Audience :: Developers
Classifier: License :: OSI Approved :: BSD License
Classifier: Operating System :: OS Independent
Classifier: Programming Language :: Python
Classifier: Programming Language :: Python :: 3
Classifier: Programming Language :: Python :: 3.8
Classifier: Programming Language :: Python :: 3.9
Classifier: Programming Language :: Python :: 3.10
Classifier: Programming Language :: Python :: 3.11
Classifier: Programming Language :: Python :: 3 :: Only
Classifier: Topic :: Software Development :: Libraries :: Python Modules
Requires-Dist: django (>=4.2,<5.0)
Requires-Dist: django-debug-toolbar (>=4.0.0)
Project-URL: Repository, https://github.com/baudhuina/djdt-permissions
